nlmunicipality/__init__.py
nlmunicipality/guess.py
nlmunicipality-1.0.2.dist-info/LICENSE.md
nlmunicipality-1.0.2.dist-info/METADATA
nlmunicipality-1.0.2.dist-info/WHEEL
nlmunicipality-1.0.2.dist-info/top_level.txt
nlmunicipality-1.0.2.dist-info/RECORD
