Metadata-Version: 2.1
Name: nlmunicipality
Version: 1.0.2
Summary: Guess official Dutch municipality name from user-provided location name
Author-email: dirkmjk <info@dirkmjk.nl>
Project-URL: Homepage, https://github.com/DIRKMJK/nlmunicipality
Keywords: municipality
Classifier: License :: OSI Approved :: MIT License
Classifier: Programming Language :: Python
Classifier: Programming Language :: Python :: 3
License-File: LICENSE.md
Requires-Dist: pandas
Requires-Dist: requests
Requires-Dist: cbsodata
Requires-Dist: fuzzywuzzy
Requires-Dist: bs4
